package com.tencent.qc.stat;

class c
  implements Runnable
{
  c(StatStore paramStatStore, s params)
  {
  }

  // ERROR //
  public void run()
  {
    // Byte code:
    //   0: aload_0
    //   1: getfield 16	com/tencent/qc/stat/c:a	Lcom/tencent/qc/stat/s;
    //   4: invokevirtual 27	com/tencent/qc/stat/s:a	()Ljava/lang/String;
    //   7: astore_1
    //   8: aload_1
    //   9: invokevirtual 33	java/lang/String:length	()I
    //   12: ifle +242 -> 254
    //   15: aload_1
    //   16: invokestatic 38	com/tencent/qc/stat/common/StatCommonHelper:a	(Ljava/lang/String;)Ljava/lang/String;
    //   19: astore_2
    //   20: aload_2
    //   21: aload_0
    //   22: getfield 16	com/tencent/qc/stat/c:a	Lcom/tencent/qc/stat/s;
    //   25: getfield 42	com/tencent/qc/stat/s:c	Ljava/lang/String;
    //   28: invokevirtual 46	java/lang/String:equals	(Ljava/lang/Object;)Z
    //   31: ifne +223 -> 254
    //   34: new 48	android/content/ContentValues
    //   37: dup
    //   38: invokespecial 49	android/content/ContentValues:<init>	()V
    //   41: astore_3
    //   42: aload_3
    //   43: ldc 51
    //   45: aload_0
    //   46: getfield 16	com/tencent/qc/stat/c:a	Lcom/tencent/qc/stat/s;
    //   49: getfield 54	com/tencent/qc/stat/s:b	Lorg/json/JSONObject;
    //   52: invokevirtual 59	org/json/JSONObject:toString	()Ljava/lang/String;
    //   55: invokevirtual 63	android/content/ContentValues:put	(Ljava/lang/String;Ljava/lang/String;)V
    //   58: aload_3
    //   59: ldc 65
    //   61: aload_2
    //   62: invokevirtual 63	android/content/ContentValues:put	(Ljava/lang/String;Ljava/lang/String;)V
    //   65: aload_0
    //   66: getfield 16	com/tencent/qc/stat/c:a	Lcom/tencent/qc/stat/s;
    //   69: aload_2
    //   70: putfield 42	com/tencent/qc/stat/s:c	Ljava/lang/String;
    //   73: aload_3
    //   74: ldc 67
    //   76: aload_0
    //   77: getfield 16	com/tencent/qc/stat/c:a	Lcom/tencent/qc/stat/s;
    //   80: getfield 71	com/tencent/qc/stat/s:d	I
    //   83: invokestatic 77	java/lang/Integer:valueOf	(I)Ljava/lang/Integer;
    //   86: invokevirtual 80	android/content/ContentValues:put	(Ljava/lang/String;Ljava/lang/Integer;)V
    //   89: aload_0
    //   90: getfield 14	com/tencent/qc/stat/c:b	Lcom/tencent/qc/stat/StatStore;
    //   93: invokestatic 85	com/tencent/qc/stat/StatStore:b	(Lcom/tencent/qc/stat/StatStore;)Lcom/tencent/qc/stat/i;
    //   96: invokevirtual 91	com/tencent/qc/stat/i:getReadableDatabase	()Landroid/database/sqlite/SQLiteDatabase;
    //   99: ldc 93
    //   101: aconst_null
    //   102: aconst_null
    //   103: aconst_null
    //   104: aconst_null
    //   105: aconst_null
    //   106: aconst_null
    //   107: invokevirtual 99	android/database/sqlite/SQLiteDatabase:query	(Ljava/lang/String;[Ljava/lang/String;Ljava/lang/String;[Ljava/lang/String;Ljava/lang/String;Ljava/lang/String;Ljava/lang/String;)Landroid/database/Cursor;
    //   110: astore 12
    //   112: aload 12
    //   114: astore 5
    //   116: aload 5
    //   118: invokeinterface 105 1 0
    //   123: ifeq +263 -> 386
    //   126: aload 5
    //   128: iconst_0
    //   129: invokeinterface 109 2 0
    //   134: istore 13
    //   136: aload_0
    //   137: getfield 16	com/tencent/qc/stat/c:a	Lcom/tencent/qc/stat/s;
    //   140: getfield 111	com/tencent/qc/stat/s:a	I
    //   143: istore 14
    //   145: iload 13
    //   147: iload 14
    //   149: if_icmpne -33 -> 116
    //   152: iconst_1
    //   153: istore 7
    //   155: aload 5
    //   157: ifnull +10 -> 167
    //   160: aload 5
    //   162: invokeinterface 114 1 0
    //   167: iconst_1
    //   168: iload 7
    //   170: if_icmpne +136 -> 306
    //   173: aload_0
    //   174: getfield 14	com/tencent/qc/stat/c:b	Lcom/tencent/qc/stat/StatStore;
    //   177: invokestatic 85	com/tencent/qc/stat/StatStore:b	(Lcom/tencent/qc/stat/StatStore;)Lcom/tencent/qc/stat/i;
    //   180: invokevirtual 117	com/tencent/qc/stat/i:getWritableDatabase	()Landroid/database/sqlite/SQLiteDatabase;
    //   183: astore 10
    //   185: iconst_1
    //   186: anewarray 29	java/lang/String
    //   189: astore 11
    //   191: aload 11
    //   193: iconst_0
    //   194: aload_0
    //   195: getfield 16	com/tencent/qc/stat/c:a	Lcom/tencent/qc/stat/s;
    //   198: getfield 111	com/tencent/qc/stat/s:a	I
    //   201: invokestatic 120	java/lang/Integer:toString	(I)Ljava/lang/String;
    //   204: aastore
    //   205: aload 10
    //   207: ldc 93
    //   209: aload_3
    //   210: ldc 122
    //   212: aload 11
    //   214: invokevirtual 126	android/database/sqlite/SQLiteDatabase:update	(Ljava/lang/String;Landroid/content/ContentValues;Ljava/lang/String;[Ljava/lang/String;)I
    //   217: i2l
    //   218: lstore 8
    //   220: lload 8
    //   222: ldc2_w 127
    //   225: lcmp
    //   226: ifne +118 -> 344
    //   229: invokestatic 131	com/tencent/qc/stat/StatStore:c	()Lcom/tencent/qc/stat/common/StatLogger;
    //   232: new 133	java/lang/StringBuilder
    //   235: dup
    //   236: invokespecial 134	java/lang/StringBuilder:<init>	()V
    //   239: ldc 136
    //   241: invokevirtual 140	java/lang/StringBuilder:append	(Ljava/lang/String;)Ljava/lang/StringBuilder;
    //   244: aload_1
    //   245: invokevirtual 140	java/lang/StringBuilder:append	(Ljava/lang/String;)Ljava/lang/StringBuilder;
    //   248: invokevirtual 141	java/lang/StringBuilder:toString	()Ljava/lang/String;
    //   251: invokevirtual 147	com/tencent/qc/stat/common/StatLogger:e	(Ljava/lang/Object;)V
    //   254: return
    //   255: astore 6
    //   257: aconst_null
    //   258: astore 5
    //   260: invokestatic 131	com/tencent/qc/stat/StatStore:c	()Lcom/tencent/qc/stat/common/StatLogger;
    //   263: aload 6
    //   265: invokevirtual 150	com/tencent/qc/stat/common/StatLogger:b	(Ljava/lang/Exception;)V
    //   268: aload 5
    //   270: ifnull +110 -> 380
    //   273: aload 5
    //   275: invokeinterface 114 1 0
    //   280: iconst_0
    //   281: istore 7
    //   283: goto -116 -> 167
    //   286: astore 4
    //   288: aconst_null
    //   289: astore 5
    //   291: aload 5
    //   293: ifnull +10 -> 303
    //   296: aload 5
    //   298: invokeinterface 114 1 0
    //   303: aload 4
    //   305: athrow
    //   306: aload_3
    //   307: ldc 152
    //   309: aload_0
    //   310: getfield 16	com/tencent/qc/stat/c:a	Lcom/tencent/qc/stat/s;
    //   313: getfield 111	com/tencent/qc/stat/s:a	I
    //   316: invokestatic 77	java/lang/Integer:valueOf	(I)Ljava/lang/Integer;
    //   319: invokevirtual 80	android/content/ContentValues:put	(Ljava/lang/String;Ljava/lang/Integer;)V
    //   322: aload_0
    //   323: getfield 14	com/tencent/qc/stat/c:b	Lcom/tencent/qc/stat/StatStore;
    //   326: invokestatic 85	com/tencent/qc/stat/StatStore:b	(Lcom/tencent/qc/stat/StatStore;)Lcom/tencent/qc/stat/i;
    //   329: invokevirtual 117	com/tencent/qc/stat/i:getWritableDatabase	()Landroid/database/sqlite/SQLiteDatabase;
    //   332: ldc 93
    //   334: aconst_null
    //   335: aload_3
    //   336: invokevirtual 156	android/database/sqlite/SQLiteDatabase:insert	(Ljava/lang/String;Ljava/lang/String;Landroid/content/ContentValues;)J
    //   339: lstore 8
    //   341: goto -121 -> 220
    //   344: invokestatic 131	com/tencent/qc/stat/StatStore:c	()Lcom/tencent/qc/stat/common/StatLogger;
    //   347: new 133	java/lang/StringBuilder
    //   350: dup
    //   351: invokespecial 134	java/lang/StringBuilder:<init>	()V
    //   354: ldc 158
    //   356: invokevirtual 140	java/lang/StringBuilder:append	(Ljava/lang/String;)Ljava/lang/StringBuilder;
    //   359: aload_1
    //   360: invokevirtual 140	java/lang/StringBuilder:append	(Ljava/lang/String;)Ljava/lang/StringBuilder;
    //   363: invokevirtual 141	java/lang/StringBuilder:toString	()Ljava/lang/String;
    //   366: invokevirtual 160	com/tencent/qc/stat/common/StatLogger:b	(Ljava/lang/Object;)V
    //   369: return
    //   370: astore 4
    //   372: goto -81 -> 291
    //   375: astore 6
    //   377: goto -117 -> 260
    //   380: iconst_0
    //   381: istore 7
    //   383: goto -216 -> 167
    //   386: iconst_0
    //   387: istore 7
    //   389: goto -234 -> 155
    //
    // Exception table:
    //   from	to	target	type
    //   89	112	255	java/lang/Exception
    //   89	112	286	finally
    //   116	145	370	finally
    //   260	268	370	finally
    //   116	145	375	java/lang/Exception
  }
}

/* Location:           /mnt/data/hpc-dev/hou/20131220/同步更新文档说明20131220/classes-dex2jar.jar
 * Qualified Name:     com.tencent.qc.stat.c
 * JD-Core Version:    0.6.0
 */